deepmd_gnn/__init__.py
deepmd_gnn/__main__.py
deepmd_gnn/_version.py
deepmd_gnn/argcheck.py
deepmd_gnn/env.py
deepmd_gnn/mace.py
deepmd_gnn/nequip.py
deepmd_gnn/op.py
deepmd_gnn/py.typed
deepmd_gnn/lib/__init__.py
deepmd_gnn/lib/libdeepmd_gnn.so
deepmd_gnn-0.1.2.dist-info/METADATA
deepmd_gnn-0.1.2.dist-info/WHEEL
deepmd_gnn-0.1.2.dist-info/entry_points.txt
deepmd_gnn-0.1.2.dist-info/RECORD
deepmd_gnn-0.1.2.dist-info/licenses/LICENSE
