Metadata-Version: 2.2
Name: deepmd-gnn
Version: 0.1.2
Summary: DeePMD-kit plugin for graph neural network models.
Author-Email: Jinzhe Zeng <jinzhe.zeng@ustc.edu.cn>
License:                    GNU LESSER GENERAL PUBLIC LICENSE
Classifier: Programming Language :: Python :: 3.9
Classifier: Programming Language :: Python :: 3.10
Classifier: Programming Language :: Python :: 3.11
Classifier: Programming Language :: Python :: 3.12
Classifier: Operating System :: POSIX :: Linux
Classifier: Operating System :: MacOS :: MacOS X
Classifier: Operating System :: Microsoft :: Windows
Classifier: License :: OSI Approved :: GNU Lesser General Public License v3 (LGPLv3)
Project-URL: repository, https://gitlab.com/RutgersLBSR/deepmd-gnn
Requires-Python: >=3.9
Requires-Dist: torch
Requires-Dist: deepmd-kit[torch]>=3.0.0
Requires-Dist: mace-torch>=0.3.5
Requires-Dist: nequip
Requires-Dist: e3nn
Requires-Dist: dargs
Provides-Extra: test
Requires-Dist: pytest; extra == "test"
Requires-Dist: pytest-cov; extra == "test"
Requires-Dist: dargs>=0.4.8; extra == "test"
Provides-Extra: docs
Requires-Dist: sphinx; extra == "docs"
Requires-Dist: sphinx-autoapi; extra == "docs"
Requires-Dist: myst-parser; extra == "docs"
Requires-Dist: deepmodeling-sphinx>=0.3.0; extra == "docs"
Requires-Dist: sphinx-book-theme; extra == "docs"
Requires-Dist: dargs; extra == "docs"
